strsim_2-1.1.1.dist-info/METADATA
strsim_2-1.1.1.dist-info/WHEEL
strsim_2-1.1.1.dist-info/license_files/LICENSE
strsim_2-1.1.1.dist-info/license_files/LICENSE
strsim/py.typed
strsim/__init__.pyi
strsim/__init__.py
strsim/strsim.cpython-38-x86_64-linux-gnu.so
strsim_2-1.1.1.dist-info/RECORD
